mcp_cuc_kkn-0.3.0.dist-info/licenses/LICENSE
mcp_time_server/__init__.py
mcp_time_server/server.py
mcp_cuc_kkn-0.3.0.dist-info/METADATA
mcp_cuc_kkn-0.3.0.dist-info/WHEEL
mcp_cuc_kkn-0.3.0.dist-info/entry_points.txt
mcp_cuc_kkn-0.3.0.dist-info/top_level.txt
mcp_cuc_kkn-0.3.0.dist-info/RECORD
