Metadata-Version: 2.4
Name: mcp-cuc-kkn
Version: 0.3.0
Summary: A simple MCP Server that provides time query functionality
Author-email: 2792427924 <2792427924@qq.com>
License: MIT
Project-URL: Homepage, https://github.com/27924/mcp-time-server
Project-URL: Repository, https://github.com/27924/mcp-time-server
Project-URL: Issues, https://github.com/27924/mcp-time-server/issues
Keywords: mcp,model-context-protocol,time,server
Classifier: Development Status :: 4 - Beta
Classifier: Intended Audience :: Developers
Classifier: License :: OSI Approved :: MIT License
Classifier: Programming Language :: Python :: 3
Classifier: Programming Language :: Python :: 3.8
Classifier: Programming Language :: Python :: 3.9
Classifier: Programming Language :: Python :: 3.10
Classifier: Programming Language :: Python :: 3.11
Classifier: Programming Language :: Python :: 3.12
Classifier: Programming Language :: Python :: 3.13
Requires-Python: >=3.8
License-File: LICENSE
Requires-Dist: mcp>=1.0.0
Requires-Dist: pytz>=2024.0
Provides-Extra: dev
Requires-Dist: pytest>=7.0; extra == "dev"
Requires-Dist: black>=23.0; extra == "dev"
Requires-Dist: mypy>=1.0; extra == "dev"
Dynamic: license-file
